shogun/__init__.py
shogun/buildutils.py
shogun/pathutil.py
shogun/platforms.py
shogun/thirdparty/ninja_syntax.py
shogun_build-0.3.2.dist-info/LICENSE
shogun_build-0.3.2.dist-info/METADATA
shogun_build-0.3.2.dist-info/WHEEL
shogun_build-0.3.2.dist-info/top_level.txt
shogun_build-0.3.2.dist-info/RECORD
