Metadata-Version: 2.1
Name: shogun-build
Version: 0.3.2
Summary: Package for facilitating the creation of Python-based build scripts using Ninja as the compilation backend. Focuses on small projects using gcc/g++.
Author-email: Brandon Alba <brandonealba@protonmail.com>
License: Copyright © 2023 Brandon Alba
Project-URL: Source, https://github.com/branalba/shogun
License-File: LICENSE
Requires-Dist: Click
